kinto/__init__.py
kinto/__main__.py
kinto/authorization.py
kinto/contribute.json
kinto/events.py
kinto/schema_validation.py
kinto/config/__init__.py
kinto/config/kinto.tpl
kinto/core/__init__.py
kinto/core/authentication.py
kinto/core/authorization.py
kinto/core/decorators.py
kinto/core/errors.py
kinto/core/events.py
kinto/core/initialization.py
kinto/core/metrics.py
kinto/core/openapi.py
kinto/core/schema.py
kinto/core/scripts.py
kinto/core/statsd.py
kinto/core/testing.py
kinto/core/utils.py
kinto/core/cache/__init__.py
kinto/core/cache/memcached.py
kinto/core/cache/memory.py
kinto/core/cache/testing.py
kinto/core/cache/postgresql/__init__.py
kinto/core/cache/postgresql/schema.sql
kinto/core/cornice/__init__.py
kinto/core/cornice/cors.py
kinto/core/cornice/errors.py
kinto/core/cornice/pyramidhook.py
kinto/core/cornice/renderer.py
kinto/core/cornice/resource.py
kinto/core/cornice/service.py
kinto/core/cornice/util.py
kinto/core/cornice/validators/__init__.py
kinto/core/cornice/validators/_colander.py
kinto/core/cornice/validators/_marshmallow.py
kinto/core/cornice_swagger/__init__.py
kinto/core/cornice_swagger/swagger.py
kinto/core/cornice_swagger/util.py
kinto/core/cornice_swagger/views.py
kinto/core/cornice_swagger/converters/__init__.py
kinto/core/cornice_swagger/converters/exceptions.py
kinto/core/cornice_swagger/converters/parameters.py
kinto/core/cornice_swagger/converters/schema.py
kinto/core/cornice_swagger/templates/index.html
kinto/core/cornice_swagger/templates/index_script_template.html
kinto/core/listeners/__init__.py
kinto/core/permission/__init__.py
kinto/core/permission/memory.py
kinto/core/permission/testing.py
kinto/core/permission/postgresql/__init__.py
kinto/core/permission/postgresql/schema.sql
kinto/core/permission/postgresql/migrations/migration_001_002.sql
kinto/core/resource/__init__.py
kinto/core/resource/model.py
kinto/core/resource/schema.py
kinto/core/resource/viewset.py
kinto/core/storage/__init__.py
kinto/core/storage/exceptions.py
kinto-23.3.2.dist-info/licenses/LICENSE
kinto-23.3.2.dist-info/METADATA
kinto-23.3.2.dist-info/WHEEL
kinto-23.3.2.dist-info/entry_points.txt
kinto-23.3.2.dist-info/top_level.txt
kinto-23.3.2.dist-info/RECORD
