Metadata-Version: 2.4
Name: kinto
Version: 23.3.2
Summary: Kinto Web Service - Store, Sync, Share, and Self-Host.
Author-email: Mozilla Services <developers@kinto-storage.org>
License: Copyright 2012 - Mozilla Foundation
Project-URL: Repository, https://github.com/Kinto/kinto
Keywords: web,sync,json,storage,services
Classifier: Programming Language :: Python
Classifier: Programming Language :: Python :: 3
Classifier: Programming Language :: Python :: 3.9
Classifier: Programming Language :: Python :: 3.10
Classifier: Programming Language :: Python :: 3.11
Classifier: Programming Language :: Python :: 3.12
Classifier: Programming Language :: Python :: Implementation :: CPython
Classifier: Topic :: Internet :: WWW/HTTP
Classifier: Topic :: Internet :: WWW/HTTP :: WSGI :: Application
Classifier: License :: OSI Approved :: Apache Software License
License-File: LICENSE
Requires-Dist: bcrypt
Requires-Dist: colander
Requires-Dist: dockerflow
Requires-Dist: jsonschema
Requires-Dist: jsonpatch
Requires-Dist: logging-color-formatter
Requires-Dist: python-dateutil
Requires-Dist: pyramid
Requires-Dist: pyramid_multiauth
Requires-Dist: transaction
Requires-Dist: pyramid_tm
Requires-Dist: requests
Requires-Dist: waitress
Requires-Dist: python-rapidjson
Provides-Extra: redis
Requires-Dist: kinto_redis; extra == "redis"
Provides-Extra: memcached
Requires-Dist: python-memcached; extra == "memcached"
Provides-Extra: postgresql
Requires-Dist: SQLAlchemy<3; extra == "postgresql"
Requires-Dist: psycopg2-binary; extra == "postgresql"
Requires-Dist: zope.sqlalchemy; extra == "postgresql"
Provides-Extra: monitoring
Requires-Dist: newrelic; extra == "monitoring"
Requires-Dist: sentry-sdk[sqlalchemy]; extra == "monitoring"
Requires-Dist: statsd; extra == "monitoring"
Requires-Dist: werkzeug; extra == "monitoring"
Requires-Dist: prometheus-client; extra == "monitoring"
Provides-Extra: test
Requires-Dist: bravado; extra == "test"
Requires-Dist: pytest; extra == "test"
Requires-Dist: pytest-cache; extra == "test"
Requires-Dist: pytest-cov; extra == "test"
Requires-Dist: playwright; extra == "test"
Requires-Dist: webtest; extra == "test"
Provides-Extra: dev
Requires-Dist: build; extra == "dev"
Requires-Dist: ruff; extra == "dev"
Requires-Dist: twine; extra == "dev"
Requires-Dist: uwsgi; extra == "dev"
Dynamic: license-file
